pandavro/__init__.py
pandavro_aa-1.9.0.dist-info/licenses/LICENSE
pandavro_aa-1.9.0.dist-info/METADATA
pandavro_aa-1.9.0.dist-info/WHEEL
pandavro_aa-1.9.0.dist-info/top_level.txt
pandavro_aa-1.9.0.dist-info/RECORD
