Metadata-Version: 2.4
Name: pandavro-aa
Version: 1.9.0
Summary: Fork of ynqa/pandavro to support newer numpy releases
Home-page: https://github.com/fredcohen-aa/pandavro
Author: Fred Cohen
Author-email: fred.cohen@aa.com
License: MIT
Requires-Python: >=3.9.0
License-File: LICENSE
Requires-Dist: fastavro<2.0.0,>=1.5.1
Requires-Dist: pandas<3.0.0,>=2.0
Requires-Dist: numpy<3.0.0,>=2.0
Provides-Extra: tests
Requires-Dist: pytest==7.3.2; extra == "tests"
Requires-Dist: tox==4.6.0; extra == "tests"
Dynamic: author
Dynamic: author-email
Dynamic: description
Dynamic: description-content-type
Dynamic: home-page
Dynamic: license
Dynamic: license-file
Dynamic: provides-extra
Dynamic: requires-dist
Dynamic: requires-python
Dynamic: summary
